teletask/__init__.py
teletask/__version__.py
teletask/client.py
teletask/test.py
teletask/core/__init__.py
teletask/core/telegram_queue.py
teletask/devices/__init__.py
teletask/devices/device.py
teletask/devices/devices.py
teletask/devices/dimmer.py
teletask/devices/light.py
teletask/devices/remote_value.py
teletask/devices/remote_value_dimmer.py
teletask/devices/remote_value_scaling.py
teletask/devices/remote_value_switch.py
teletask/devices/switch.py
teletask/doip/__init__.py
teletask/doip/frame.py
teletask/doip/telegram.py
teletask/doip/test.py
teletask/exceptions/__init__.py
teletask/exceptions/exception.py
teletask/io/__init__.py
teletask/io/client.py
teletask/io/doip_interface.py
pyteletask-1.0.5.dist-info/METADATA
pyteletask-1.0.5.dist-info/WHEEL
pyteletask-1.0.5.dist-info/top_level.txt
pyteletask-1.0.5.dist-info/RECORD
