Metadata-Version: 2.1
Name: pyteletask
Version: 1.0.5
Summary: An Asynchronous Library for the Teletask protocol.
Author: Timothy DE MEY
Author-email: timothy.demey@edisonn.io
License: MIT
Keywords: teletask ip teletaskdoip doip home automation
Classifier: Development Status :: 3 - Alpha
Classifier: Intended Audience :: End Users/Desktop
Classifier: Intended Audience :: Developers
Classifier: Topic :: System :: Hardware :: Hardware Drivers
Classifier: License :: OSI Approved :: MIT License
Classifier: Programming Language :: Python :: 3.5
Classifier: Programming Language :: Python :: 3.6
